MANIFEST.in
README.md
setup.py
pyetcdlock/__init__.py
pyetcdlock/lock.py
pyetcdlock.egg-info/PKG-INFO
pyetcdlock.egg-info/SOURCES.txt
pyetcdlock.egg-info/dependency_links.txt
pyetcdlock.egg-info/requires.txt
pyetcdlock.egg-info/top_level.txt